{
  "component_type": "dagster_component_templates.AzureStreamAnalyticsComponent",
  "description": "Component for importing Azure Stream Analytics entities as Dagster assets.",
  "category": "integration",
  "icon": "si:microsoftazure",
  "x-dagster-io": {
    "outputs": {
      "type": "MaterializeResult",
      "description": "Integration result"
    }
  },
  "attributes": {
    "subscription_id": {
      "type": "string",
      "label": "Subscription Id",
      "description": "Azure subscription ID",
      "required": true,
      "ui:widget": "code"
    },
    "resource_group_name": {
      "type": "string",
      "label": "Resource Group Name",
      "description": "Azure resource group name",
      "required": true
    },
    "tenant_id": {
      "type": "string",
      "label": "Tenant Id",
      "description": "Tenant Id",
      "required": false,
      "default": null
    },
    "client_id": {
      "type": "string",
      "label": "Client Id",
      "description": "Client Id",
      "required": false,
      "default": null
    },
    "client_secret": {
      "type": "string",
      "label": "Client Secret",
      "description": "Client Secret",
      "required": false,
      "default": null,
      "ui:widget": "password"
    },
    "import_streaming_jobs": {
      "type": "boolean",
      "label": "Import Streaming Jobs",
      "description": "Import streaming jobs as materializable assets",
      "required": false,
      "default": true,
      "ui:widget": "checkbox"
    },
    "filter_by_name_pattern": {
      "type": "string",
      "label": "Filter By Name Pattern",
      "description": "Regex pattern to filter entities by name",
      "required": false,
      "default": null
    },
    "exclude_name_pattern": {
      "type": "string",
      "label": "Exclude Name Pattern",
      "description": "Regex pattern to exclude entities by name",
      "required": false,
      "default": null
    },
    "filter_by_tags": {
      "type": "string",
      "label": "Filter By Tags",
      "description": "Comma-separated tag keys to filter entities (e.g., ",
      "required": false,
      "default": null
    },
    "poll_interval_seconds": {
      "type": "integer",
      "label": "Poll Interval Seconds",
      "description": "Sensor poll interval in seconds",
      "required": false,
      "default": 60
    },
    "generate_sensor": {
      "type": "boolean",
      "label": "Generate Sensor",
      "description": "Generate observation sensor for streaming job status",
      "required": false,
      "default": true,
      "ui:widget": "checkbox"
    },
    "group_name": {
      "type": "string",
      "label": "Group Name",
      "description": "Asset group name for all imported assets",
      "required": false,
      "default": "azure_stream_analytics"
    },
    "description": {
      "type": "string",
      "label": "Description",
      "description": "Description for the Azure Stream Analytics component",
      "required": false,
      "default": null,
      "ui:widget": "code"
    }
  },
  "tags": [
    "integration",
    "azure",
    "stream",
    "analytics"
  ]
}